README.rst
setup.py
pycu/__init__.py
pycu.egg-info/PKG-INFO
pycu.egg-info/SOURCES.txt
pycu.egg-info/dependency_links.txt
pycu.egg-info/requires.txt
pycu.egg-info/top_level.txt