Metadata-Version: 1.1
Name: pycu
Version: 0.2.0
Summary: PyICU Wrapper
Home-page: http://github.com/meyt/pycu
Author: Mahdi Ghane.g
Author-email: UNKNOWN
License: MIT
Keywords: pyicu icu localization internationalization i18n calendar locale
Platform: UNKNOWN
Classifier: Development Status :: 3 - Alpha
Classifier: Intended Audience :: Developers
Classifier: License :: OSI Approved :: MIT License
Classifier: Operating System :: POSIX :: Linux
Classifier: Operating System :: Unix
Classifier: Programming Language :: Python :: 3 :: Only
Classifier: Topic :: Software Development :: Internationalization
Classifier: Topic :: Software Development :: Localization
Classifier: Topic :: Software Development :: Libraries
